Workbook

Sheet Eingaben
A1: Eingaben – Rahmendaten Hauskauf (gelbe Felder sind editierbar)
A3: Haus & Kaufnebenkosten
A4: Kaufpreis Haus (noch offen – Schätzung) | B4: 400000 | C4: Platzhalter – sobald der Preis feststeht, hier eintragen.
A5: Grunderwerbsteuer (% vom Kaufpreis) | B5: 0.065 | C5: Je nach Bundesland 3,5 % bis 6,5 %.
A6: Notar & Grundbuch (% vom Kaufpreis) | B6: 0.02 | C6: Üblich sind ca. 1,5 % bis 2 %.
A7: Maklerprovision (% vom Kaufpreis) | B7: 0.0357 | C7: Käuferanteil, oft 3,57 % inkl. MwSt.; 0 % wenn ohne Makler.
A8: Renovierung / Umzug / Küche (einmalig) | B8: 20000 | C8: Einmalige Kosten rund um den Einzug.
A10: Finanzierung
A11: Eigenkapital-Einsatz (% des einsetzbaren Vermögens) | B11: 0.9 | C11: Wie viel des Vermögens (Blatt „Vermögen“, Spalte „einsetzbar“) fließt in den Kauf. Rest bleibt Reserve.
A12: Kaufjahr | B12: 2026 | C12: Startjahr für Tilgungsplan und „abbezahlt im Jahr“.

Sheet Einnahmen
A1: Einnahmen (Zeilen 4–15 frei editierbar / ergänzbar)
A2: Hinweis: Netto-Beträge eintragen. „jährlich“ wird automatisch durch 12 geteilt.
A3: Position | B3: Betrag (€) | C3: Intervall | D3: pro Monat (€)
A4: Nettogehalt Person 1 | B4: 3200 | C4: monatlich | D4: =IF($B4="","",IF($C4="jährlich",$B4/12,$B4))
A5: Nettogehalt Person 2 | B5: 2400 | C5: monatlich | D5: =IF($B5="","",IF($C5="jährlich",$B5/12,$B5))
A6: Kindergeld | B6: 255 | C6: monatlich | D6: =IF($B6="","",IF($C6="jährlich",$B6/12,$B6))
A7: Weihnachts-/Urlaubsgeld | B7: 2500 | C7: jährlich | D7: =IF($B7="","",IF($C7="jährlich",$B7/12,$B7))
A8: Steuererstattung | B8: 1200 | C8: jährlich | D8: =IF($B8="","",IF($C8="jährlich",$B8/12,$B8))
D9: =IF($B9="","",IF($C9="jährlich",$B9/12,$B9))
D10: =IF($B10="","",IF($C10="jährlich",$B10/12,$B10))
D11: =IF($B11="","",IF($C11="jährlich",$B11/12,$B11))
D12: =IF($B12="","",IF($C12="jährlich",$B12/12,$B12))
D13: =IF($B13="","",IF($C13="jährlich",$B13/12,$B13))
D14: =IF($B14="","",IF($C14="jährlich",$B14/12,$B14))
D15: =IF($B15="","",IF($C15="jährlich",$B15/12,$B15))
A17: Summe Einnahmen pro Monat | D17: =SUM(D4:D15)

Sheet Ausgaben
A1: Ausgaben (Zeilen 4–15 frei editierbar / ergänzbar)
A2: WICHTIG: Ausgaben-Situation NACH dem Kauf eintragen – also OHNE aktuelle Kaltmiete und OHNE Kreditrate (die berechnet die Kalkulation). Nebenkosten des Hauses (Strom, Heizung, Grundsteuer …) gehören hier hinein.
A3: Position | B3: Betrag (€) | C3: Intervall | D3: pro Monat (€)
A4: Lebenshaltung (Essen, Drogerie, Kleidung) | B4: 1400 | C4: monatlich | D4: =IF($B4="","",IF($C4="jährlich",$B4/12,$B4))
A5: Strom / Heizung / Wasser (Haus) | B5: 350 | C5: monatlich | D5: =IF($B5="","",IF($C5="jährlich",$B5/12,$B5))
A6: Auto & Mobilität | B6: 300 | C6: monatlich | D6: =IF($B6="","",IF($C6="jährlich",$B6/12,$B6))
A7: Versicherungen | B7: 1800 | C7: jährlich | D7: =IF($B7="","",IF($C7="jährlich",$B7/12,$B7))
A8: Urlaub | B8: 3000 | C8: jährlich | D8: =IF($B8="","",IF($C8="jährlich",$B8/12,$B8))
A9: Kommunikation (Handy, Internet, Streaming) | B9: 100 | C9: monatlich | D9: =IF($B9="","",IF($C9="jährlich",$B9/12,$B9))
A10: Grundsteuer & Müllgebühren | B10: 800 | C10: jährlich | D10: =IF($B10="","",IF($C10="jährlich",$B10/12,$B10))
A11: Sonstiges / Puffer | B11: 200 | C11: monatlich | D11: =IF($B11="","",IF($C11="jährlich",$B11/12,$B11))
D12: =IF($B12="","",IF($C12="jährlich",$B12/12,$B12))
D13: =IF($B13="","",IF($C13="jährlich",$B13/12,$B13))
D14: =IF($B14="","",IF($C14="jährlich",$B14/12,$B14))
D15: =IF($B15="","",IF($C15="jährlich",$B15/12,$B15))
A17: Summe Ausgaben pro Monat | D17: =SUM(D4:D15)

Sheet Vermögen
A1: Vermögen (Zeilen 4–12 frei editierbar / ergänzbar)
A2: Nur Positionen mit „ja“ zählen als einsetzbares Eigenkapital. Notgroschen auf „nein“ setzen.
A3: Position | B3: Wert (€) | C3: für Hauskauf einsetzbar? | D3: einsetzbar (€)
A4: Tagesgeld | B4: 60000 | C4: ja | D4: =IF($B4="","",IF($C4="ja",$B4,0))
A5: ETF-Depot | B5: 40000 | C5: ja | D5: =IF($B5="","",IF($C5="ja",$B5,0))
A6: Bausparvertrag | B6: 15000 | C6: ja | D6: =IF($B6="","",IF($C6="ja",$B6,0))
A7: Notgroschen (bleibt unangetastet) | B7: 15000 | C7: nein | D7: =IF($B7="","",IF($C7="ja",$B7,0))
D8: =IF($B8="","",IF($C8="ja",$B8,0))
D9: =IF($B9="","",IF($C9="ja",$B9,0))
D10: =IF($B10="","",IF($C10="ja",$B10,0))
D11: =IF($B11="","",IF($C11="ja",$B11,0))
D12: =IF($B12="","",IF($C12="ja",$B12,0))
A14: Gesamtvermögen | B14: =SUM(B4:B12)
A15: davon für Hauskauf einsetzbar | D15: =SUM(D4:D12)

Sheet Kalkulation
A1: Kalkulation – Was kostet der Kauf und wann ist das Haus abbezahlt?
A3: 1) Gesamtkosten des Kaufs
A4: Kaufpreis | B4: ='Eingaben'!B4
A5: Grunderwerbsteuer | B5: ='Eingaben'!B4*'Eingaben'!B5 | E5: = Kaufpreis × Steuersatz
A6: Notar & Grundbuch | B6: ='Eingaben'!B4*'Eingaben'!B6 | E6: = Kaufpreis × Satz
A7: Maklerprovision | B7: ='Eingaben'!B4*'Eingaben'!B7 | E7: = Kaufpreis × Satz
A8: Renovierung / Umzug / Küche | B8: ='Eingaben'!B8 | E8: einmalig, aus Eingaben
A9: Gesamtkosten | B9: =SUM(B4:B8) | E9: = Kaufpreis + alle Nebenkosten + Einmalkosten
A11: 2) Eigenkapital & Darlehen
A12: Eigenkapital-Einsatz | B12: ='Vermögen'!D15*'Eingaben'!B11 | E12: = einsetzbares Vermögen × Eigenkapital-Quote
A13: Darlehensbedarf | B13: =MAX(0,B9-B12) | E13: = Gesamtkosten − Eigenkapital
A14: Beleihungsauslauf (Darlehen ÷ Kaufpreis) | B14: =B13/B4 | E14: über ca. 90 % verlangen Banken deutliche Zinsaufschläge
A16: 3) Monatlicher Haushalt
A17: Einnahmen pro Monat | B17: ='Einnahmen'!D17
A18: Ausgaben pro Monat (ohne Miete/Kreditrate) | B18: ='Ausgaben'!D17
A19: Überschuss pro Monat | B19: =B17-B18
A21: 4) Szenarien – wann ist das Haus abbezahlt? (Parameter in Zeilen 23–26 editierbar)
A22: Szenario | B22: Optimistisch | C22: Basis | D22: Risiko | E22: Risiko = höherer (Anschluss-)Zins, weniger Einkommen, mehr Instandhaltung
A23: Sollzins p.a. | B23: 0.032 | C23: 0.038 | D23: 0.05 | E23: angenommener Zins über die gesamte Laufzeit
A24: Sicherheitsabschlag auf Einnahmen | B24: 0 | C24: 0.05 | D24: 0.1 | E24: Puffer für Jobwechsel, Elternzeit, Krankheit …
A25: Instandhaltungsrücklage pro Monat | B25: 200 | C25: 300 | D25: 400 | E25: Faustregel: 2–3 € je m² Wohnfläche und Monat
A26: Anteil des Überschusses für die Kreditrate | B26: 1 | C26: 0.85 | D26: 0.8 | E26: Rest bleibt als freier monatlicher Puffer
A27: Überschuss nach Abschlag & Rücklage | B27: =$B$17*(1-B24)-$B$18-B25 | C27: =$B$17*(1-C24)-$B$18-C25 | D27: =$B$17*(1-D24)-$B$18-D25 | E27: = Einnahmen × (1 − Abschlag) − Ausgaben − Rücklage
A28: monatliche Kreditrate | B28: =MAX(0,B27*B26) | C28: =MAX(0,C27*C26) | D28: =MAX(0,D27*D26) | E28: = Überschuss (Z. 27) × Anteil (Z. 26)
A29: anfängliche Tilgung p.a. | B29: =IF(B28=0,"–",(B28*12-$B$13*B23)/$B$13) | C29: =IF(C28=0,"–",(C28*12-$B$13*C23)/$B$13) | D29: =IF(D28=0,"–",(D28*12-$B$13*D23)/$B$13) | E29: = (Jahresrate − Zinsen 1. Jahr) ÷ Darlehen; Banken erwarten meist ≥ 2 %
A30: Laufzeit in Monaten | B30: =IFERROR(ROUND(NPER(B23/12,-B28,$B$13),0),"nie – Rate zu niedrig!") | C30: =IFERROR(ROUND(NPER(C23/12,-C28,$B$13),0),"nie – Rate zu niedrig!") | D30: =IFERROR(ROUND(NPER(D23/12,-D28,$B$13),0),"nie – Rate zu niedrig!") | E30: = NPER(Zins/12; −Rate; Darlehen), s. Blatt Erläuterungen
A31: Laufzeit in Jahren | B31: =IFERROR(ROUND(NPER(B23/12,-B28,$B$13)/12,1),"–") | C31: =IFERROR(ROUND(NPER(C23/12,-C28,$B$13)/12,1),"–") | D31: =IFERROR(ROUND(NPER(D23/12,-D28,$B$13)/12,1),"–")
A32: Haus abbezahlt im Jahr | B32: =IFERROR('Eingaben'!$B$12+ROUNDUP(NPER(B23/12,-B28,$B$13)/12,0),"nie") | C32: =IFERROR('Eingaben'!$B$12+ROUNDUP(NPER(C23/12,-C28,$B$13)/12,0),"nie") | D32: =IFERROR('Eingaben'!$B$12+ROUNDUP(NPER(D23/12,-D28,$B$13)/12,0),"nie") | E32: = Kaufjahr + aufgerundete Laufzeit
A33: dafür insgesamt gezahlte Zinsen | B33: =IFERROR(NPER(B23/12,-B28,$B$13)*B28-$B$13,"–") | C33: =IFERROR(NPER(C23/12,-C28,$B$13)*C28-$B$13,"–") | D33: =IFERROR(NPER(D23/12,-D28,$B$13)*D28-$B$13,"–") | E33: = Rate × Monate − Darlehen
A35: Alle Formeln sind im Blatt „Erläuterungen“ Schritt für Schritt erklärt.

Sheet Tilgungsplan
A1: Tilgungsplan – Jahr für Jahr (Basis-Szenario)
A2: Annahme: Zins und Rate konstant, keine Sondertilgung. Formeln s. Blatt „Erläuterungen“.
B3: Darlehen | C3: ='Kalkulation'!B13
B4: Sollzins p.a. (Basis) | C4: ='Kalkulation'!C23
B5: Monatsrate (Basis) | C5: ='Kalkulation'!C28
A7: Jahr | B7: Restschuld Jahresanfang | C7: Zinsen im Jahr | D7: Tilgung im Jahr | E7: Restschuld Jahresende
A8: ='Eingaben'!B12 | B8: =$C$3 | C8: =IF(B8<=0,0,IF(E8>0,12*$C$5-D8,IFERROR(NPER($C$4/12,-$C$5,B8)*$C$5-B8,0))) | D8: =B8-E8 | E8: =IF(B8<=0,0,MAX(0,B8*(1+$C$4/12)^12-$C$5*(((1+$C$4/12)^12-1)/($C$4/12))))
A9: =A8+1 | B9: =E8 | C9: =IF(B9<=0,0,IF(E9>0,12*$C$5-D9,IFERROR(NPER($C$4/12,-$C$5,B9)*$C$5-B9,0))) | D9: =B9-E9 | E9: =IF(B9<=0,0,MAX(0,B9*(1+$C$4/12)^12-$C$5*(((1+$C$4/12)^12-1)/($C$4/12))))
A10: =A9+1 | B10: =E9 | C10: =IF(B10<=0,0,IF(E10>0,12*$C$5-D10,IFERROR(NPER($C$4/12,-$C$5,B10)*$C$5-B10,0))) | D10: =B10-E10 | E10: =IF(B10<=0,0,MAX(0,B10*(1+$C$4/12)^12-$C$5*(((1+$C$4/12)^12-1)/($C$4/12))))
A11: =A10+1 | B11: =E10 | C11: =IF(B11<=0,0,IF(E11>0,12*$C$5-D11,IFERROR(NPER($C$4/12,-$C$5,B11)*$C$5-B11,0))) | D11: =B11-E11 | E11: =IF(B11<=0,0,MAX(0,B11*(1+$C$4/12)^12-$C$5*(((1+$C$4/12)^12-1)/($C$4/12))))
A12: =A11+1 | B12: =E11 | C12: =IF(B12<=0,0,IF(E12>0,12*$C$5-D12,IFERROR(NPER($C$4/12,-$C$5,B12)*$C$5-B12,0))) | D12: =B12-E12 | E12: =IF(B12<=0,0,MAX(0,B12*(1+$C$4/12)^12-$C$5*(((1+$C$4/12)^12-1)/($C$4/12))))
A13: =A12+1 | B13: =E12 | C13: =IF(B13<=0,0,IF(E13>0,12*$C$5-D13,IFERROR(NPER($C$4/12,-$C$5,B13)*$C$5-B13,0))) | D13: =B13-E13 | E13: =IF(B13<=0,0,MAX(0,B13*(1+$C$4/12)^12-$C$5*(((1+$C$4/12)^12-1)/($C$4/12))))
A14: =A13+1 | B14: =E13 | C14: =IF(B14<=0,0,IF(E14>0,12*$C$5-D14,IFERROR(NPER($C$4/12,-$C$5,B14)*$C$5-B14,0))) | D14: =B14-E14 | E14: =IF(B14<=0,0,MAX(0,B14*(1+$C$4/12)^12-$C$5*(((1+$C$4/12)^12-1)/($C$4/12))))
A15: =A14+1 | B15: =E14 | C15: =IF(B15<=0,0,IF(E15>0,12*$C$5-D15,IFERROR(NPER($C$4/12,-$C$5,B15)*$C$5-B15,0))) | D15: =B15-E15 | E15: =IF(B15<=0,0,MAX(0,B15*(1+$C$4/12)^12-$C$5*(((1+$C$4/12)^12-1)/($C$4/12))))
A16: =A15+1 | B16: =E15 | C16: =IF(B16<=0,0,IF(E16>0,12*$C$5-D16,IFERROR(NPER($C$4/12,-$C$5,B16)*$C$5-B16,0))) | D16: =B16-E16 | E16: =IF(B16<=0,0,MAX(0,B16*(1+$C$4/12)^12-$C$5*(((1+$C$4/12)^12-1)/($C$4/12))))
A17: =A16+1 | B17: =E16 | C17: =IF(B17<=0,0,IF(E17>0,12*$C$5-D17,IFERROR(NPER($C$4/12,-$C$5,B17)*$C$5-B17,0))) | D17: =B17-E17 | E17: =IF(B17<=0,0,MAX(0,B17*(1+$C$4/12)^12-$C$5*(((1+$C$4/12)^12-1)/($C$4/12))))
A18: =A17+1 | B18: =E17 | C18: =IF(B18<=0,0,IF(E18>0,12*$C$5-D18,IFERROR(NPER($C$4/12,-$C$5,B18)*$C$5-B18,0))) | D18: =B18-E18 | E18: =IF(B18<=0,0,MAX(0,B18*(1+$C$4/12)^12-$C$5*(((1+$C$4/12)^12-1)/($C$4/12))))
A19: =A18+1 | B19: =E18 | C19: =IF(B19<=0,0,IF(E19>0,12*$C$5-D19,IFERROR(NPER($C$4/12,-$C$5,B19)*$C$5-B19,0))) | D19: =B19-E19 | E19: =IF(B19<=0,0,MAX(0,B19*(1+$C$4/12)^12-$C$5*(((1+$C$4/12)^12-1)/($C$4/12))))
A20: =A19+1 | B20: =E19 | C20: =IF(B20<=0,0,IF(E20>0,12*$C$5-D20,IFERROR(NPER($C$4/12,-$C$5,B20)*$C$5-B20,0))) | D20: =B20-E20 | E20: =IF(B20<=0,0,MAX(0,B20*(1+$C$4/12)^12-$C$5*(((1+$C$4/12)^12-1)/($C$4/12))))
... A47: =A46+1 | B47: =E46 | C47: =IF(B47<=0,0,IF(E47>0,12*$C$5-D47,IFERROR(NPER($C$4/12,-$C$5,B47)*$C$5-B47,0))) | D47: =B47-E47 | E47: =IF(B47<=0,0,MAX(0,B47*(1+$C$4/12)^12-$C$5*(((1+$C$4/12)^12-1)/($C$4/12))))

Sheet Erläuterungen
A1: Erläuterungen – so funktioniert die Kalkulation
A3: 1) Aufbau & Farben
A4: GELBE Felder = Eingaben, die du frei ändern kannst. Alles andere rechnet sich automatisch neu.
A5: GRAUE Felder = berechnete Zwischenwerte, GRÜNE Felder = zentrale Ergebnisse. Beides bitte nicht überschreiben.
A6: Blätter: Eingaben (Rahmendaten) → Einnahmen / Ausgaben / Vermögen (Listen) → Kalkulation (Ergebnis) → Tilgungsplan (Jahr für Jahr).
A8: 2) Einnahmen, Ausgaben, Vermögen
A9: In den Listen sind bis Zeile 15 (Vermögen: Zeile 12) Formeln vorbereitet – einfach neue Positionen in leere Zeilen eintragen.
A10: Intervall „jährlich“ wird automatisch umgerechnet: pro Monat = Betrag ÷ 12.
A11: WICHTIG bei Ausgaben: Situation NACH dem Kauf eintragen – keine aktuelle Kaltmiete (entfällt) und keine Kreditrate (wird berechnet).
A12: Vermögen: Nur Zeilen mit „ja“ fließen als Eigenkapital ein. So bleibt z. B. der Notgroschen („nein“) geschützt.
A14: 3) Gesamtkosten des Kaufs (Blatt Kalkulation, Zeilen 4–9)
A15: Jede Nebenkostenposition = Kaufpreis × Prozentsatz aus dem Blatt Eingaben.
... A59: Alle verwendeten Funktionen (SUM, IF, MAX, NPER, IFERROR, ROUND, ROUNDUP) funktionieren dort identisch.
